FedCL/__init__.py
FedCL/aggregators/aggregator.py
FedCL/aggregators/distances.py
FedCL/aggregators/fedopt_aggregator.py
FedCL/aggregators/temperature.py
FedCL/data_structures/cluster_sturcutre.py
FedCL/files/archive.py
FedCL/files/handlers.py
FedCL/files/loggers.py
FedCL/model/federated_model.py
FedCL/node/federated_node.py
FedCL/operations/evaluations.py
FedCL/operations/orchestrations.py
FedCL/simulation/simulation.py
FedCL/utils/animation.py
FedCL/utils/computations.py
FedCL/utils/select_gradients.py
FedCL/utils/splitters.py
fedcl-0.1.1.dist-info/LICENSE
fedcl-0.1.1.dist-info/METADATA
fedcl-0.1.1.dist-info/WHEEL
fedcl-0.1.1.dist-info/RECORD
